spider/__init__.py
spider/__main__.py
spider/proxy.py
rainbow_spider_proxy-1.0.2.dist-info/METADATA
rainbow_spider_proxy-1.0.2.dist-info/WHEEL
rainbow_spider_proxy-1.0.2.dist-info/top_level.txt
rainbow_spider_proxy-1.0.2.dist-info/RECORD
